bits/__init__.py
bits/dialpad/__init__.py
bits/dialpad/reports.py
bits_dialpad-1.0.11.dist-info/METADATA
bits_dialpad-1.0.11.dist-info/WHEEL
bits_dialpad-1.0.11.dist-info/top_level.txt
bits_dialpad-1.0.11.dist-info/RECORD
