Metadata-Version: 2.1
Name: bits-dialpad
Version: 1.0.11
Summary: BITS Dialpad
Home-page: UNKNOWN
Author: Lukas Karlsson
Author-email: karlsson@broadinstitute.org
License: Apache Software License
Platform: UNKNOWN
